simplemath_leonardosantosdev/__init__.py
simplemath_leonardosantosdev/__main__.py
simplemath_leonardosantosdev/arithmetic.py
simplemath_leonardosantosdev/cli_opts.py
simplemath_leonardosantosdev-0.1.3.dist-info/LICENCE
simplemath_leonardosantosdev-0.1.3.dist-info/METADATA
simplemath_leonardosantosdev-0.1.3.dist-info/WHEEL
simplemath_leonardosantosdev-0.1.3.dist-info/entry_points.txt
simplemath_leonardosantosdev-0.1.3.dist-info/top_level.txt
simplemath_leonardosantosdev-0.1.3.dist-info/RECORD
