Metadata-Version: 2.1
Name: simplemath-leonardosantosdev
Version: 0.1.3
Summary: A simple math operations package
Home-page: https://github.com/leonardosantosdev/simplemath_leonardosantosdev
Author: Leonardo Santos
Author-email: leodossantosldsl@gmail.com
Classifier: Programming Language :: Python :: 3
Classifier: License :: OSI Approved :: MIT License
Classifier: Operating System :: OS Independent
Requires-Python: >=3.6
License-File: LICENCE
